docker_mcp/__init__.py
docker_mcp/__main__.py
docker_mcp/config.py
docker_mcp/container_ops.py
docker_mcp/deps.py
docker_mcp/docker_client.py
docker_mcp/schemas.py
docker_mcp/server.py
docker_mcp_sdk-0.1.0.dist-info/licenses/LICENSE
docker_mcp_sdk-0.1.0.dist-info/METADATA
docker_mcp_sdk-0.1.0.dist-info/WHEEL
docker_mcp_sdk-0.1.0.dist-info/entry_points.txt
docker_mcp_sdk-0.1.0.dist-info/top_level.txt
docker_mcp_sdk-0.1.0.dist-info/RECORD
