Metadata-Version: 2.4
Name: docker-mcp-sdk
Version: 0.1.0
Summary: A Model Context Protocol server for secure Docker container execution
Author-email: Kerim Incedayi <k@kerim.me>
Maintainer-email: Kerim Incedayi <k@kerim.me>
License: MIT
Project-URL: Homepage, https://github.com/cevatkerim/docker-mcp
Project-URL: Documentation, https://github.com/cevatkerim/docker-mcp#readme
Project-URL: Repository, https://github.com/cevatkerim/docker-mcp.git
Project-URL: Issues, https://github.com/cevatkerim/docker-mcp/issues
Keywords: mcp,docker,container,sandbox,llm,ai,code-execution
Classifier: Development Status :: 4 - Beta
Classifier: Intended Audience :: Developers
Classifier: License :: OSI Approved :: MIT License
Classifier: Operating System :: OS Independent
Classifier: Programming Language :: Python :: 3
Classifier: Programming Language :: Python :: 3.10
Classifier: Programming Language :: Python :: 3.11
Classifier: Programming Language :: Python :: 3.12
Classifier: Topic :: Software Development :: Libraries :: Python Modules
Classifier: Topic :: System :: Distributed Computing
Requires-Python: >=3.10
License-File: LICENSE
Requires-Dist: docker>=7.0.0
Requires-Dist: fastmcp>=0.1.0
Requires-Dist: pydantic>=2.0.0
Provides-Extra: dev
Requires-Dist: pytest>=7.0; extra == "dev"
Requires-Dist: pytest-asyncio>=0.23; extra == "dev"
Requires-Dist: pytest-mock>=3.10; extra == "dev"
Requires-Dist: pytest-cov>=4.0; extra == "dev"
Requires-Dist: types-docker; extra == "dev"
Requires-Dist: black>=23.0; extra == "dev"
Requires-Dist: ruff>=0.1.0; extra == "dev"
Requires-Dist: mypy>=1.0; extra == "dev"
Dynamic: license-file
